{
  "!type": "GoogleMap",
  "apiKey": "AIzaSyCDQAMt2_CtE-JHQUWTqNsKECMc4QRTI18",
  "background": "",
  "bottom": "0",
  "cached_js": "",
  "cached_js_script_hash": "d41d8cd98f00b204e9800998ecf8427e",
  "children": [],
  "class": "",
  "disableDefaultUI": false,
  "disableDoubleClickZoom": true,
  "display": "",
  "draggable": true,
  "draggableCursor": "",
  "draggingCursor": "",
  "expanded_pmp": null,
  "heading": 0,
  "height": "460",
  "hidden": "",
  "id": "gmpClinic",
  "keyboardShortcuts": true,
  "latitude": "",
  "left": "0",
  "longitude": "",
  "mapMaker": false,
  "mapTypeId": "roadmap",
  "maxZoom": 20,
  "minZoom": 0,
  "noClear": false,
  "onclick": "",
  "onmousedown": "",
  "onmousemove": "",
  "onmouseout": "",
  "onmouseup": "",
  "onresize": "",
  "ontouchend": "",
  "ontouchmove": "",
  "ontouchstart": "",
  "right": "0",
  "script": "",
  "scrollwheel": true,
  "streetViewControl": true,
  "style": "",
  "tilt": 0,
  "top": "0",
  "width": "320",
  "zoom": 16,
  "zoomControl": true
}